docstring_type_tag_checker/__init__.py
docstring_type_tag_checker/base_docstring_type.py
docstring_type_tag_checker/docstring_types/__init__.py
docstring_type_tag_checker/docstring_types/function_type.py
docstring_type_tag_checker/docstring_types/generic_type.py
docstring_type_tag_checker/docstring_types/string_type.py
docstring_type_tag_checker/docstring_types/tuple_type.py
docstring_type_tag_checker/docstring_types/union_type.py
docstring_type_tag_checker-1.0.dist-info/METADATA
docstring_type_tag_checker-1.0.dist-info/WHEEL
docstring_type_tag_checker-1.0.dist-info/top_level.txt
docstring_type_tag_checker-1.0.dist-info/RECORD
