Metadata-Version: 2.1
Name: docstring-type-tag-checker
Version: 1.0
Summary: package to check syntax of type tags in docstring
Author: Marc MALBERT
Author-email: marc.malbert@capgemini.com
Classifier: Programming Language :: Python :: 3
Classifier: Development Status :: 5 - Production/Stable
Classifier: Natural Language :: English
Classifier: Operating System :: OS Independent
